{
  "last_updated": "2026-03-09T04:45:19.211723",
  "count": 228,
  "exhibitions": [
    {
      "title": "赤松孝「ROAD RACING」",
      "start_date": "2026-02-03",
      "end_date": "2026-02-14",
      "location": "キヤノンギャラリー銀座",
      "date_text": "2/3～14",
      "link": "https://getnavi.jp/capa/exhibition/tokyo/",
      "tag": "exhibition"
    },
    {
      "title": "高島空太「頭がいっぱいでも意識して。」",
      "start_date": "2026-02-17",
      "end_date": "2026-02-28",
      "location": "キヤノンギャラリー銀座",
      "date_text": "2/17～28",
      "link": "https://getnavi.jp/capa/exhibition/tokyo/",
      "tag": "exhibition"
    },
    {
      "title": "戸塚学「飾り鳥 ～お部屋を彩る野鳥～」",
      "start_date": "2026-03-03",
      "end_date": "2026-03-14",
      "location": "キヤノンギャラリー銀座",
      "date_text": "3/3～14",
      "link": "https://getnavi.jp/capa/exhibition/tokyo/",
      "tag": "exhibition"
    },
    {
      "title": "龍神孝介「スンバワ 島の伝統競馬と少年騎手」",
      "start_date": "2026-03-17",
      "end_date": "2026-03-28",
      "location": "キヤノンギャラリー銀座",
      "date_text": "3/17～28",
      "link": "https://getnavi.jp/capa/exhibition/tokyo/",
      "tag": "exhibition"
    },
    {
      "title": "ミラノ・コルティナ2026 報道写真展",
      "start_date": "2026-03-31",
      "end_date": "2026-04-11",
      "location": "キヤノンギャラリー銀座",
      "date_text": "3/31～4/11",
      "link": "https://getnavi.jp/capa/exhibition/tokyo/",
      "tag": "exhibition"
    },
    {
      "title": "MAMORU ATSUTA「600GP The Champions」",
      "start_date": "2026-02-04",
      "end_date": "2026-02-12",
      "location": "CO-CO PHOTO SALON",
      "date_text": "2/4～12",
      "link": "https://getnavi.jp/capa/exhibition/tokyo/",
      "tag": "exhibition"
    },
    {
      "title": "大村英明「記憶の色彩 in CUBA」",
      "start_date": "2026-02-18",
      "end_date": "2026-02-26",
      "location": "CO-CO PHOTO SALON",
      "date_text": "2/18～26",
      "link": "https://getnavi.jp/capa/exhibition/tokyo/",
      "tag": "exhibition"
    },
    {
      "title": "キセキミチコ「Dhuvam -煙霧の地ネパール-」",
      "start_date": "2026-03-18",
      "end_date": "2026-03-26",
      "location": "CO-CO PHOTO SALON",
      "date_text": "3/18～26",
      "link": "https://getnavi.jp/capa/exhibition/tokyo/",
      "tag": "exhibition"
    },
    {
      "title": "鈴木渉「Everest Eats」",
      "start_date": "2026-01-30",
      "end_date": "2026-02-12",
      "location": "ソニーイメージングギャラリー",
      "date_text": "1/30～2/12",
      "link": "https://getnavi.jp/capa/exhibition/tokyo/",
      "tag": "exhibition"
    },
    {
      "title": "広瀬慎也「京に残された大自然 芦生の森」(2/17休館)",
      "start_date": "2026-02-13",
      "end_date": "2026-02-26",
      "location": "ソニーイメージングギャラリー",
      "date_text": "2/13～26",
      "link": "https://getnavi.jp/capa/exhibition/tokyo/",
      "tag": "exhibition"
    },
    {
      "title": "小林優希「はこふぃぐめんと」",
      "start_date": "2026-02-27",
      "end_date": "2026-03-12",
      "location": "ソニーイメージングギャラリー",
      "date_text": "2/27～3/12",
      "link": "https://getnavi.jp/capa/exhibition/tokyo/",
      "tag": "exhibition"
    },
    {
      "title": "東京工芸大学芸術学部写真学科卒業制作選抜 Recommend展2026",
      "start_date": "2026-03-13",
      "end_date": "2026-03-19",
      "location": "ソニーイメージングギャラリー",
      "date_text": "3/13～19",
      "link": "https://getnavi.jp/capa/exhibition/tokyo/",
      "tag": "exhibition"
    },
    {
      "title": "Maki「MYSTERY」",
      "start_date": "2026-01-24",
      "end_date": "2026-02-13",
      "location": "ソニーストア銀座",
      "date_text": "1/24～2/13",
      "link": "https://getnavi.jp/capa/exhibition/tokyo/",
      "tag": "exhibition"
    },
    {
      "title": "中央大学理工学部写真会「静止したシネマ」",
      "start_date": "2026-02-14",
      "end_date": "2026-02-28",
      "location": "ソニーストア銀座",
      "date_text": "2/14～28",
      "link": "https://getnavi.jp/capa/exhibition/tokyo/",
      "tag": "exhibition"
    },
    {
      "title": "フラワーフォトクラブ「植物たちの四季」",
      "start_date": "2026-01-30",
      "end_date": "2026-02-05",
      "location": "富士フォトギャラリー銀座",
      "date_text": "1/30～2/5",
      "link": "https://getnavi.jp/capa/exhibition/tokyo/",
      "tag": "exhibition"
    },
    {
      "title": "IPCC写真倶楽部「おもいのままに “身近な風景から”」",
      "start_date": "2026-02-06",
      "end_date": "2026-02-12",
      "location": "富士フォトギャラリー銀座",
      "date_text": "2/6～12",
      "link": "https://getnavi.jp/capa/exhibition/tokyo/",
      "tag": "exhibition"
    },
    {
      "title": "第46回 三菱合同写真展",
      "start_date": "2026-02-13",
      "end_date": "2026-02-19",
      "location": "富士フォトギャラリー銀座",
      "date_text": "2/13～19",
      "link": "https://getnavi.jp/capa/exhibition/tokyo/",
      "tag": "exhibition"
    },
    {
      "title": "村上悠太 ドクターイエロー写真展「ありがとう T4」-T4がその使命を終えるまでの物語-",
      "start_date": "2026-02-20",
      "end_date": "2026-02-26",
      "location": "富士フォトギャラリー銀座",
      "date_text": "2/20～26",
      "link": "https://getnavi.jp/capa/exhibition/tokyo/",
      "tag": "exhibition"
    },
    {
      "title": "フォトグループエンジョイ「Let’s Enjoy！ 2026」",
      "start_date": "2026-02-27",
      "end_date": "2026-03-05",
      "location": "富士フォトギャラリー銀座",
      "date_text": "2/27～3/5",
      "link": "https://getnavi.jp/capa/exhibition/tokyo/",
      "tag": "exhibition"
    },
    {
      "title": "美菜子塾「Another Moment またとない瞬間2」",
      "start_date": "2026-03-06",
      "end_date": "2026-03-12",
      "location": "富士フォトギャラリー銀座",
      "date_text": "3/6～12",
      "link": "https://getnavi.jp/capa/exhibition/tokyo/",
      "tag": "exhibition"
    },
    {
      "title": "ニッコールクラブ東銀座写游支部 (写游会) 第24回写真展",
      "start_date": "2026-03-13",
      "end_date": "2026-03-19",
      "location": "富士フォトギャラリー銀座",
      "date_text": "3/13～19",
      "link": "https://getnavi.jp/capa/exhibition/tokyo/",
      "tag": "exhibition"
    },
    {
      "title": "第四回 日本の流景展 with International Panning Foto Award 2026",
      "start_date": "2026-03-20",
      "end_date": "2026-03-26",
      "location": "富士フォトギャラリー銀座",
      "date_text": "3/20～26",
      "link": "https://getnavi.jp/capa/exhibition/tokyo/",
      "tag": "exhibition"
    },
    {
      "title": "鶴田裕「鉄道写真 昭和29年−昭和33年 ～蘇るカラーポジフィルムの記録と記憶～」",
      "start_date": "2026-03-27",
      "end_date": "2026-04-02",
      "location": "富士フォトギャラリー銀座",
      "date_text": "3/27～4/2",
      "link": "https://getnavi.jp/capa/exhibition/tokyo/",
      "tag": "exhibition"
    },
    {
      "title": "村上悠太 ドクターイエロー写真展「ありがとう T4」-T4がその使命を終えるまでの物語-",
      "start_date": "2026-02-20",
      "end_date": "2026-02-26",
      "location": "富士フォトギャラリー銀座",
      "date_text": "2/20～26",
      "link": "https://getnavi.jp/capa/exhibition/tokyo/",
      "tag": "exhibition"
    },
    {
      "title": "第16回 こだわり花クラブ写真展",
      "start_date": "2026-02-27",
      "end_date": "2026-03-05",
      "location": "富士フォトギャラリー銀座",
      "date_text": "2/27～3/5",
      "link": "https://getnavi.jp/capa/exhibition/tokyo/",
      "tag": "exhibition"
    },
    {
      "title": "坪井智洋「歩き、歩む、」",
      "start_date": "2026-03-06",
      "end_date": "2026-03-12",
      "location": "富士フォトギャラリー銀座",
      "date_text": "3/6～12",
      "link": "https://getnavi.jp/capa/exhibition/tokyo/",
      "tag": "exhibition"
    },
    {
      "title": "第四回 日本の流景展 with International Panning Foto Award 2026",
      "start_date": "2026-03-20",
      "end_date": "2026-03-26",
      "location": "富士フォトギャラリー銀座",
      "date_text": "3/20～26",
      "link": "https://getnavi.jp/capa/exhibition/tokyo/",
      "tag": "exhibition"
    },
    {
      "title": "鶴田裕「鉄道写真 昭和29年−昭和33年 ～蘇るカラーポジフィルムの記録と記憶～」",
      "start_date": "2026-03-27",
      "end_date": "2026-04-02",
      "location": "富士フォトギャラリー銀座",
      "date_text": "3/27～4/2",
      "link": "https://getnavi.jp/capa/exhibition/tokyo/",
      "tag": "exhibition"
    },
    {
      "title": "nabe ＆ Chihiro「#キミと巡る季節 50年後のキミへ To You, 50 Years from Now」",
      "start_date": "2026-01-30",
      "end_date": "2026-02-05",
      "location": "富士フォトギャラリー銀座",
      "date_text": "1/30～2/5",
      "link": "https://getnavi.jp/capa/exhibition/tokyo/",
      "tag": "exhibition"
    },
    {
      "title": "第46回 三菱合同写真展",
      "start_date": "2026-02-13",
      "end_date": "2026-02-19",
      "location": "富士フォトギャラリー銀座",
      "date_text": "2/13～19",
      "link": "https://getnavi.jp/capa/exhibition/tokyo/",
      "tag": "exhibition"
    },
    {
      "title": "村上悠太 ドクターイエロー写真展「ありがとう T4」-T4がその使命を終えるまでの物語-",
      "start_date": "2026-02-20",
      "end_date": "2026-02-26",
      "location": "富士フォトギャラリー銀座",
      "date_text": "2/20～26",
      "link": "https://getnavi.jp/capa/exhibition/tokyo/",
      "tag": "exhibition"
    },
    {
      "title": "神戸正行「自由変幻」",
      "start_date": "2026-03-06",
      "end_date": "2026-03-12",
      "location": "富士フォトギャラリー銀座",
      "date_text": "3/6～12",
      "link": "https://getnavi.jp/capa/exhibition/tokyo/",
      "tag": "exhibition"
    },
    {
      "title": "第四回 日本の流景展 with International Panning Foto Award 2026",
      "start_date": "2026-03-20",
      "end_date": "2026-03-26",
      "location": "富士フォトギャラリー銀座",
      "date_text": "3/20～26",
      "link": "https://getnavi.jp/capa/exhibition/tokyo/",
      "tag": "exhibition"
    },
    {
      "title": "和田浩×小林弘雄「森林鉄道のおもひで」",
      "start_date": "2026-03-27",
      "end_date": "2026-04-02",
      "location": "富士フォトギャラリー銀座",
      "date_text": "3/27～4/2",
      "link": "https://getnavi.jp/capa/exhibition/tokyo/",
      "tag": "exhibition"
    },
    {
      "title": "nabe ＆ Chihiro「#キミと巡る季節 50年後のキミへ To You, 50 Years from Now」",
      "start_date": "2026-01-30",
      "end_date": "2026-02-05",
      "location": "富士フォトギャラリー銀座",
      "date_text": "1/30～2/5",
      "link": "https://getnavi.jp/capa/exhibition/tokyo/",
      "tag": "exhibition"
    },
    {
      "title": "のんびりカメラサークル アクティブ支部 Exhibition MONO-LOGUE",
      "start_date": "2026-02-13",
      "end_date": "2026-02-19",
      "location": "富士フォトギャラリー銀座",
      "date_text": "2/13～19",
      "link": "https://getnavi.jp/capa/exhibition/tokyo/",
      "tag": "exhibition"
    },
    {
      "title": "村上悠太 ドクターイエロー写真展「ありがとう T4」-T4がその使命を終えるまでの物語-",
      "start_date": "2026-02-20",
      "end_date": "2026-02-26",
      "location": "富士フォトギャラリー銀座",
      "date_text": "2/20～26",
      "link": "https://getnavi.jp/capa/exhibition/tokyo/",
      "tag": "exhibition"
    },
    {
      "title": "神戸正行「自由変幻」",
      "start_date": "2026-03-06",
      "end_date": "2026-03-12",
      "location": "富士フォトギャラリー銀座",
      "date_text": "3/6～12",
      "link": "https://getnavi.jp/capa/exhibition/tokyo/",
      "tag": "exhibition"
    },
    {
      "title": "山内昭子「里ごころ 荒川のほとり、いま。」",
      "start_date": "2026-03-13",
      "end_date": "2026-03-19",
      "location": "富士フォトギャラリー銀座",
      "date_text": "3/13～19",
      "link": "https://getnavi.jp/capa/exhibition/tokyo/",
      "tag": "exhibition"
    },
    {
      "title": "第四回 日本の流景展 with International Panning Foto Award 2026",
      "start_date": "2026-03-20",
      "end_date": "2026-03-26",
      "location": "富士フォトギャラリー銀座",
      "date_text": "3/20～26",
      "link": "https://getnavi.jp/capa/exhibition/tokyo/",
      "tag": "exhibition"
    },
    {
      "title": "ウスキヨシミ「ある窓」",
      "start_date": "2026-03-27",
      "end_date": "2026-04-02",
      "location": "富士フォトギャラリー銀座",
      "date_text": "3/27～4/2",
      "link": "https://getnavi.jp/capa/exhibition/tokyo/",
      "tag": "exhibition"
    },
    {
      "title": "ワーナー・ビショフ「ビショフの見た戦後 ～普遍たるもの～」",
      "start_date": "2026-01-16",
      "end_date": "2026-04-19",
      "location": "ライカギャラリー東京【ライカ銀座店2F】",
      "date_text": "1/16～4/19",
      "link": "https://getnavi.jp/capa/exhibition/tokyo/",
      "tag": "exhibition"
    },
    {
      "title": "横田徹「ウクライナ狂想曲」",
      "start_date": "2026-01-16",
      "end_date": "2026-04-18",
      "location": "ライカプロフェッショナルストア東京【ライカ銀座店2F】",
      "date_text": "1/16～4/18",
      "link": "https://getnavi.jp/capa/exhibition/tokyo/",
      "tag": "exhibition"
    },
    {
      "title": "佐藤健寿写真展",
      "start_date": "2026-11-14",
      "end_date": "2026-02-12",
      "location": "ライカ GINZA SIX【GINZA SIX 5F】",
      "date_text": "11/14～2/12",
      "link": "https://getnavi.jp/capa/exhibition/tokyo/",
      "tag": "exhibition"
    },
    {
      "title": "石井朋彦「100年目のウェッツラー 100年先のライカ」",
      "start_date": "2026-02-13",
      "end_date": "2026-06-15",
      "location": "ライカ GINZA SIX【GINZA SIX 5F】",
      "date_text": "2/13～6/15",
      "link": "https://getnavi.jp/capa/exhibition/tokyo/",
      "tag": "exhibition"
    },
    {
      "title": "ウジェーヌ・アジェ写真展 – VI「シュルレアリスム」",
      "start_date": "2026-02-02",
      "end_date": "2026-02-28",
      "location": "Art Gallery M84",
      "date_text": "2/2～28",
      "link": "https://getnavi.jp/capa/exhibition/tokyo/",
      "tag": "exhibition"
    },
    {
      "title": "トニ・メネグッツォ「ポートフォリオシリーズなど」",
      "start_date": "2026-03-02",
      "end_date": "2026-04-04",
      "location": "Art Gallery M84",
      "date_text": "3/2～4/4",
      "link": "https://getnavi.jp/capa/exhibition/tokyo/",
      "tag": "exhibition"
    },
    {
      "title": "モノクロ写真展「Individual Linen Print」",
      "start_date": "2026-03-02",
      "end_date": "2026-04-04",
      "location": "Art Gallery M84",
      "date_text": "3/2～4/4",
      "link": "https://getnavi.jp/capa/exhibition/tokyo/",
      "tag": "exhibition"
    },
    {
      "title": "Spring Comes Early",
      "start_date": "2026-02-10",
      "end_date": "2026-02-15",
      "location": "GALLERY ART HOUSE",
      "date_text": "2/10～15",
      "link": "https://getnavi.jp/capa/exhibition/tokyo/",
      "tag": "exhibition"
    },
    {
      "title": "吉田祥平「SLEEP, EAT, THINK」Limelight 2025 Under40部門 グランプリ作品",
      "start_date": "2026-02-05",
      "end_date": "2026-02-16",
      "location": "OM SYSTEM PLAZA",
      "date_text": "2/5～16",
      "link": "https://getnavi.jp/capa/exhibition/tokyo/",
      "tag": "exhibition"
    },
    {
      "title": "林幸恵「Only Time ～愛しい時間～」",
      "start_date": "2026-02-19",
      "end_date": "2026-03-02",
      "location": "OM SYSTEM PLAZA",
      "date_text": "2/19～3/2",
      "link": "https://getnavi.jp/capa/exhibition/tokyo/",
      "tag": "exhibition"
    },
    {
      "title": "山下大祐「新幹線 高速度のイメージ」",
      "start_date": "2026-03-05",
      "end_date": "2026-03-16",
      "location": "OM SYSTEM PLAZA",
      "date_text": "3/5～16",
      "link": "https://getnavi.jp/capa/exhibition/tokyo/",
      "tag": "exhibition"
    },
    {
      "title": "青木勝「JET SONG II」",
      "start_date": "2026-03-19",
      "end_date": "2026-03-30",
      "location": "OM SYSTEM PLAZA",
      "date_text": "3/19～30",
      "link": "https://getnavi.jp/capa/exhibition/tokyo/",
      "tag": "exhibition"
    },
    {
      "title": "生越文明「かつての私との対話 -無意識からの始まり-」",
      "start_date": "2026-02-05",
      "end_date": "2026-02-16",
      "location": "OM SYSTEM PLAZA",
      "date_text": "2/5～16",
      "link": "https://getnavi.jp/capa/exhibition/tokyo/",
      "tag": "exhibition"
    },
    {
      "title": "田口郁明「淡海光彩 III」",
      "start_date": "2026-02-19",
      "end_date": "2026-03-02",
      "location": "OM SYSTEM PLAZA",
      "date_text": "2/19～3/2",
      "link": "https://getnavi.jp/capa/exhibition/tokyo/",
      "tag": "exhibition"
    },
    {
      "title": "鉄道写真公募展2026「私の鉄道写真」",
      "start_date": "2026-03-05",
      "end_date": "2026-03-16",
      "location": "OM SYSTEM PLAZA",
      "date_text": "3/5～16",
      "link": "https://getnavi.jp/capa/exhibition/tokyo/",
      "tag": "exhibition"
    },
    {
      "title": "青木栄隆「ちょっとJapanese II」",
      "start_date": "2026-03-19",
      "end_date": "2026-03-30",
      "location": "OM SYSTEM PLAZA",
      "date_text": "3/19～30",
      "link": "https://getnavi.jp/capa/exhibition/tokyo/",
      "tag": "exhibition"
    },
    {
      "title": "小西弘晃「City of Whispers」Limelight 2024 Under30部門 グランプリ作品",
      "start_date": "2026-02-05",
      "end_date": "2026-02-16",
      "location": "OM SYSTEM PLAZA",
      "date_text": "2/5～16",
      "link": "https://getnavi.jp/capa/exhibition/tokyo/",
      "tag": "exhibition"
    },
    {
      "title": "OM SYSTEM フォトコンテスト2025 優秀作品展",
      "start_date": "2026-02-19",
      "end_date": "2026-03-02",
      "location": "OM SYSTEM PLAZA",
      "date_text": "2/19～3/2",
      "link": "https://getnavi.jp/capa/exhibition/tokyo/",
      "tag": "exhibition"
    },
    {
      "title": "OM SYSTEM 鉄道部「鉄道旅情 (てつたび)」",
      "start_date": "2026-03-05",
      "end_date": "2026-03-16",
      "location": "OM SYSTEM PLAZA",
      "date_text": "3/5～16",
      "link": "https://getnavi.jp/capa/exhibition/tokyo/",
      "tag": "exhibition"
    },
    {
      "title": "田川基成「北海道」(2/11休館)",
      "start_date": "2026-02-03",
      "end_date": "2026-02-16",
      "location": "ニコンプラザ東京",
      "date_text": "2/3～16",
      "link": "https://getnavi.jp/capa/exhibition/tokyo/",
      "tag": "exhibition"
    },
    {
      "title": "小野陽平「繰り返される都市」",
      "start_date": "2026-02-17",
      "end_date": "2026-03-02",
      "location": "ニコンプラザ東京",
      "date_text": "2/17～3/2",
      "link": "https://getnavi.jp/capa/exhibition/tokyo/",
      "tag": "exhibition"
    },
    {
      "title": "澤田光伸「Over the Clown」",
      "start_date": "2026-03-03",
      "end_date": "2026-03-16",
      "location": "ニコンプラザ東京",
      "date_text": "3/3～16",
      "link": "https://getnavi.jp/capa/exhibition/tokyo/",
      "tag": "exhibition"
    },
    {
      "title": "ニコンサロン年度賞受賞作品展 第50回 (2025年度) 伊奈信男賞",
      "start_date": "2026-03-17",
      "end_date": "2026-03-30",
      "location": "ニコンプラザ東京",
      "date_text": "3/17～30",
      "link": "https://getnavi.jp/capa/exhibition/tokyo/",
      "tag": "exhibition"
    },
    {
      "title": "ニコンサロン年度賞受賞作品展 第27回 (2025年度) 三木淳賞",
      "start_date": "2026-03-31",
      "end_date": "2026-04-13",
      "location": "ニコンプラザ東京",
      "date_text": "3/31～4/13",
      "link": "https://getnavi.jp/capa/exhibition/tokyo/",
      "tag": "exhibition"
    },
    {
      "title": "写真専攻 大学・専門学校選抜作品展 New Generation Photography 2026(2/11休館)",
      "start_date": "2026-02-03",
      "end_date": "2026-02-16",
      "location": "ニコンプラザ東京",
      "date_text": "2/3～16",
      "link": "https://getnavi.jp/capa/exhibition/tokyo/",
      "tag": "exhibition"
    },
    {
      "title": "PHOTO HUBメンバーズ Pickup！写真展",
      "start_date": "2026-02-17",
      "end_date": "2026-03-02",
      "location": "ニコンプラザ東京",
      "date_text": "2/17～3/2",
      "link": "https://getnavi.jp/capa/exhibition/tokyo/",
      "tag": "exhibition"
    },
    {
      "title": "深澤武「桜」",
      "start_date": "2026-03-03",
      "end_date": "2026-03-16",
      "location": "ニコンプラザ東京",
      "date_text": "3/3～16",
      "link": "https://getnavi.jp/capa/exhibition/tokyo/",
      "tag": "exhibition"
    },
    {
      "title": "2025年度 TopEyeフォトコンテスト入賞作品展",
      "start_date": "2026-03-17",
      "end_date": "2026-03-30",
      "location": "ニコンプラザ東京",
      "date_text": "3/17～30",
      "link": "https://getnavi.jp/capa/exhibition/tokyo/",
      "tag": "exhibition"
    },
    {
      "title": "小川千夏「消えゆく肖像」",
      "start_date": "2026-03-31",
      "end_date": "2026-04-13",
      "location": "ニコンプラザ東京",
      "date_text": "3/31～4/13",
      "link": "https://getnavi.jp/capa/exhibition/tokyo/",
      "tag": "exhibition"
    },
    {
      "title": "ニコンカレッジ受講生作品展",
      "start_date": "2026-01-29",
      "end_date": "2026-02-07",
      "location": "ニコンプラザ東京",
      "date_text": "1/29～2/7",
      "link": "https://getnavi.jp/capa/exhibition/tokyo/",
      "tag": "exhibition"
    },
    {
      "title": "深谷美和子「北の大地のヒコーキ物語 II ～札幌丘珠空港～」",
      "start_date": "2026-03-20",
      "end_date": "2026-03-28",
      "location": "ニコンプラザ東京",
      "date_text": "3/20～28",
      "link": "https://getnavi.jp/capa/exhibition/tokyo/",
      "tag": "exhibition"
    },
    {
      "title": "佐藤健寿写真展",
      "start_date": "2026-11-14",
      "end_date": "2026-02-12",
      "location": "ライカ伊勢丹新宿店【伊勢丹新宿店メンズ館8F】",
      "date_text": "11/14～2/12",
      "link": "https://getnavi.jp/capa/exhibition/tokyo/",
      "tag": "exhibition"
    },
    {
      "title": "柏木善郎「View of Silence 02」",
      "start_date": "2026-01-29",
      "end_date": "2026-02-04",
      "location": "アイデムフォトギャラリー「シリウス」",
      "date_text": "1/29～2/4",
      "link": "https://getnavi.jp/capa/exhibition/tokyo/",
      "tag": "exhibition"
    },
    {
      "title": "Photo Unit J12 Vol.6",
      "start_date": "2026-02-05",
      "end_date": "2026-02-11",
      "location": "アイデムフォトギャラリー「シリウス」",
      "date_text": "2/5～11",
      "link": "https://getnavi.jp/capa/exhibition/tokyo/",
      "tag": "exhibition"
    },
    {
      "title": "中島康夫「日常の辺縁、記憶との邂逅」",
      "start_date": "2026-02-12",
      "end_date": "2026-02-18",
      "location": "アイデムフォトギャラリー「シリウス」",
      "date_text": "2/12～18",
      "link": "https://getnavi.jp/capa/exhibition/tokyo/",
      "tag": "exhibition"
    },
    {
      "title": "第14回 日韓中高校生フォトコンテスト写真展",
      "start_date": "2026-02-19",
      "end_date": "2026-02-25",
      "location": "アイデムフォトギャラリー「シリウス」",
      "date_text": "2/19～25",
      "link": "https://getnavi.jp/capa/exhibition/tokyo/",
      "tag": "exhibition"
    },
    {
      "title": "瀬野芙美香「アンマトータム -母なる庭で-」",
      "start_date": "2026-02-26",
      "end_date": "2026-03-04",
      "location": "アイデムフォトギャラリー「シリウス」",
      "date_text": "2/26～3/4",
      "link": "https://getnavi.jp/capa/exhibition/tokyo/",
      "tag": "exhibition"
    },
    {
      "title": "松井一泰「ドリームランド」",
      "start_date": "2026-03-05",
      "end_date": "2026-03-11",
      "location": "アイデムフォトギャラリー「シリウス」",
      "date_text": "3/5～11",
      "link": "https://getnavi.jp/capa/exhibition/tokyo/",
      "tag": "exhibition"
    },
    {
      "title": "写真を楽しむ仲間 せせらぎ「どうしましょ Choices」",
      "start_date": "2026-03-12",
      "end_date": "2026-03-18",
      "location": "アイデムフォトギャラリー「シリウス」",
      "date_text": "3/12～18",
      "link": "https://getnavi.jp/capa/exhibition/tokyo/",
      "tag": "exhibition"
    },
    {
      "title": "数見二郎「散歩の途中で III」",
      "start_date": "2026-03-19",
      "end_date": "2026-03-25",
      "location": "アイデムフォトギャラリー「シリウス」",
      "date_text": "3/19～25",
      "link": "https://getnavi.jp/capa/exhibition/tokyo/",
      "tag": "exhibition"
    },
    {
      "title": "小坂元「ロカンタンの箱庭」",
      "start_date": "2026-03-26",
      "end_date": "2026-04-01",
      "location": "アイデムフォトギャラリー「シリウス」",
      "date_text": "3/26～4/1",
      "link": "https://getnavi.jp/capa/exhibition/tokyo/",
      "tag": "exhibition"
    },
    {
      "title": "高橋ひとみ「母と」",
      "start_date": "2026-01-26",
      "end_date": "2026-02-08",
      "location": "ギャラリー蒼穹舎",
      "date_text": "1/26～2/8",
      "link": "https://getnavi.jp/capa/exhibition/tokyo/",
      "tag": "exhibition"
    },
    {
      "title": "石間秀耶「アベリアの丘」",
      "start_date": "2026-02-09",
      "end_date": "2026-02-22",
      "location": "ギャラリー蒼穹舎",
      "date_text": "2/9～22",
      "link": "https://getnavi.jp/capa/exhibition/tokyo/",
      "tag": "exhibition"
    },
    {
      "title": "上瀧由布子「あまもよいII」",
      "start_date": "2026-02-23",
      "end_date": "2026-03-08",
      "location": "ギャラリー蒼穹舎",
      "date_text": "2/23～3/8",
      "link": "https://getnavi.jp/capa/exhibition/tokyo/",
      "tag": "exhibition"
    },
    {
      "title": "コウノジュンイチ「風と水」",
      "start_date": "2026-03-09",
      "end_date": "2026-03-15",
      "location": "ギャラリー蒼穹舎",
      "date_text": "3/9～15",
      "link": "https://getnavi.jp/capa/exhibition/tokyo/",
      "tag": "exhibition"
    },
    {
      "title": "コウノジュンイチ「半々」",
      "start_date": "2026-03-16",
      "end_date": "2026-03-22",
      "location": "ギャラリー蒼穹舎",
      "date_text": "3/16～22",
      "link": "https://getnavi.jp/capa/exhibition/tokyo/",
      "tag": "exhibition"
    },
    {
      "title": "鹿野晴男写真展",
      "start_date": "2026-03-23",
      "end_date": "2026-04-05",
      "location": "ギャラリー蒼穹舎",
      "date_text": "3/23～4/5",
      "link": "https://getnavi.jp/capa/exhibition/tokyo/",
      "tag": "exhibition"
    },
    {
      "title": "藤本篤史「切れない臍の緒」",
      "start_date": "2026-02-03",
      "end_date": "2026-02-15",
      "location": "TOTEM POLE PHOTO GALLERY",
      "date_text": "2/3～15",
      "link": "https://getnavi.jp/capa/exhibition/tokyo/",
      "tag": "exhibition"
    },
    {
      "title": "ジョン サイパル「随写 vol.27」",
      "start_date": "2026-02-17",
      "end_date": "2026-03-01",
      "location": "TOTEM POLE PHOTO GALLERY",
      "date_text": "2/17～3/1",
      "link": "https://getnavi.jp/capa/exhibition/tokyo/",
      "tag": "exhibition"
    },
    {
      "title": "陳陽「刻霧裁風」",
      "start_date": "2026-03-03",
      "end_date": "2026-03-08",
      "location": "TOTEM POLE PHOTO GALLERY",
      "date_text": "3/3～8",
      "link": "https://getnavi.jp/capa/exhibition/tokyo/",
      "tag": "exhibition"
    },
    {
      "title": "土佐和史「THE SUNLIGHT TOURS」",
      "start_date": "2026-03-10",
      "end_date": "2026-03-15",
      "location": "TOTEM POLE PHOTO GALLERY",
      "date_text": "3/10～15",
      "link": "https://getnavi.jp/capa/exhibition/tokyo/",
      "tag": "exhibition"
    },
    {
      "title": "王超冉「BEYOND TOKYO」",
      "start_date": "2026-03-24",
      "end_date": "2026-03-29",
      "location": "TOTEM POLE PHOTO GALLERY",
      "date_text": "3/24～29",
      "link": "https://getnavi.jp/capa/exhibition/tokyo/",
      "tag": "exhibition"
    },
    {
      "title": "浜昇の戦後と昭和 Vol.1 浜昇「津軽野」",
      "start_date": "2026-01-26",
      "end_date": "2026-02-08",
      "location": "photographers’ gallery",
      "date_text": "1/26～2/8",
      "link": "https://getnavi.jp/capa/exhibition/tokyo/",
      "tag": "exhibition"
    },
    {
      "title": "岸幸太「連荘 16」",
      "start_date": "2026-01-09",
      "end_date": "2026-02-08",
      "location": "photographers’ gallery",
      "date_text": "1/9～2/8",
      "link": "https://getnavi.jp/capa/exhibition/tokyo/",
      "tag": "exhibition"
    },
    {
      "title": "瀬戸正人「Silent Mode 1945 New Book」",
      "start_date": "2026-02-02",
      "end_date": "2026-02-08",
      "location": "PLACE M",
      "date_text": "2/2～8",
      "link": "https://getnavi.jp/capa/exhibition/tokyo/",
      "tag": "exhibition"
    },
    {
      "title": "松浦竜一「都市の記憶」",
      "start_date": "2026-02-09",
      "end_date": "2026-02-15",
      "location": "PLACE M",
      "date_text": "2/9～15",
      "link": "https://getnavi.jp/capa/exhibition/tokyo/",
      "tag": "exhibition"
    },
    {
      "title": "吟茜「サイアムの煌き / Radiance of SIAM」",
      "start_date": "2026-02-16",
      "end_date": "2026-02-22",
      "location": "PLACE M",
      "date_text": "2/16～22",
      "link": "https://getnavi.jp/capa/exhibition/tokyo/",
      "tag": "exhibition"
    },
    {
      "title": "劉碧玲「時間紋理」",
      "start_date": "2026-03-02",
      "end_date": "2026-03-15",
      "location": "PLACE M",
      "date_text": "3/2～15",
      "link": "https://getnavi.jp/capa/exhibition/tokyo/",
      "tag": "exhibition"
    },
    {
      "title": "瀬戸正人「Silent Mode 1945 New Book」",
      "start_date": "2026-02-02",
      "end_date": "2026-02-08",
      "location": "PLACE M",
      "date_text": "2/2～8",
      "link": "https://getnavi.jp/capa/exhibition/tokyo/",
      "tag": "exhibition"
    },
    {
      "title": "アンドラス・イクラディ「浮世 / The Floating World」",
      "start_date": "2026-02-09",
      "end_date": "2026-02-22",
      "location": "PLACE M",
      "date_text": "2/9～22",
      "link": "https://getnavi.jp/capa/exhibition/tokyo/",
      "tag": "exhibition"
    },
    {
      "title": "劉碧玲「時間紋理」",
      "start_date": "2026-03-02",
      "end_date": "2026-03-15",
      "location": "PLACE M",
      "date_text": "3/2～15",
      "link": "https://getnavi.jp/capa/exhibition/tokyo/",
      "tag": "exhibition"
    },
    {
      "title": "木村英一郎「Stereotype」",
      "start_date": "2026-02-02",
      "end_date": "2026-02-15",
      "location": "RED Photo Gallery",
      "date_text": "2/2～15",
      "link": "https://getnavi.jp/capa/exhibition/tokyo/",
      "tag": "exhibition"
    },
    {
      "title": "RED Book Fair",
      "start_date": "2026-02-16",
      "end_date": "2026-02-22",
      "location": "RED Photo Gallery",
      "date_text": "2/16～22",
      "link": "https://getnavi.jp/capa/exhibition/tokyo/",
      "tag": "exhibition"
    },
    {
      "title": "ノエル3人展",
      "start_date": "2026-02-23",
      "end_date": "2026-03-01",
      "location": "RED Photo Gallery",
      "date_text": "2/23～3/1",
      "link": "https://getnavi.jp/capa/exhibition/tokyo/",
      "tag": "exhibition"
    },
    {
      "title": "小松透「New Horizon」",
      "start_date": "2026-03-02",
      "end_date": "2026-03-15",
      "location": "RED Photo Gallery",
      "date_text": "3/2～15",
      "link": "https://getnavi.jp/capa/exhibition/tokyo/",
      "tag": "exhibition"
    },
    {
      "title": "高橋和孝写真展",
      "start_date": "2026-03-16",
      "end_date": "2026-03-29",
      "location": "RED Photo Gallery",
      "date_text": "3/16～29",
      "link": "https://getnavi.jp/capa/exhibition/tokyo/",
      "tag": "exhibition"
    },
    {
      "title": "佐藤圭司写真展",
      "start_date": "2026-03-30",
      "end_date": "2026-04-12",
      "location": "RED Photo Gallery",
      "date_text": "3/30～4/12",
      "link": "https://getnavi.jp/capa/exhibition/tokyo/",
      "tag": "exhibition"
    },
    {
      "title": "小林稔 報道写真・作品展「CHASING GRACE」",
      "start_date": "2026-12-19",
      "end_date": "2026-02-03",
      "location": "キヤノン Sタワー",
      "date_text": "12/19～2/3",
      "link": "https://getnavi.jp/capa/exhibition/tokyo/",
      "tag": "exhibition"
    },
    {
      "title": "岩木登「南八甲田」",
      "start_date": "2026-02-06",
      "end_date": "2026-03-23",
      "location": "キヤノン Sタワー",
      "date_text": "2/6～3/23",
      "link": "https://getnavi.jp/capa/exhibition/tokyo/",
      "tag": "exhibition"
    },
    {
      "title": "野村恵子「龍宮」",
      "start_date": "2026-03-26",
      "end_date": "2026-05-11",
      "location": "キヤノン Sタワー",
      "date_text": "3/26～5/11",
      "link": "https://getnavi.jp/capa/exhibition/tokyo/",
      "tag": "exhibition"
    },
    {
      "title": "日本建築写真家協会「古今駅集 しらずの駅舎」",
      "start_date": "2026-01-30",
      "end_date": "2026-03-05",
      "location": "キヤノン Sタワー",
      "date_text": "1/30～3/5",
      "link": "https://getnavi.jp/capa/exhibition/tokyo/",
      "tag": "exhibition"
    },
    {
      "title": "上吉川祐一「Rebirth いのちのかたち」",
      "start_date": "2026-03-06",
      "end_date": "2026-04-09",
      "location": "キヤノン Sタワー",
      "date_text": "3/6～4/9",
      "link": "https://getnavi.jp/capa/exhibition/tokyo/",
      "tag": "exhibition"
    },
    {
      "title": "2025年度『フォトコン』月例コンテスト 推薦・金賞受賞作品展",
      "start_date": "2026-01-30",
      "end_date": "2026-03-05",
      "location": "キヤノン Sタワー",
      "date_text": "1/30～3/5",
      "link": "https://getnavi.jp/capa/exhibition/tokyo/",
      "tag": "exhibition"
    },
    {
      "title": "専門学校 東京ビジュアルアーツ・アカデミー 選抜展",
      "start_date": "2026-03-06",
      "end_date": "2026-03-23",
      "location": "キヤノン Sタワー",
      "date_text": "3/6～23",
      "link": "https://getnavi.jp/capa/exhibition/tokyo/",
      "tag": "exhibition"
    },
    {
      "title": "2025年度 日本写真映像専門学校 卒業制作・学年末制作選抜展",
      "start_date": "2026-03-24",
      "end_date": "2026-04-09",
      "location": "キヤノン Sタワー",
      "date_text": "3/24～4/9",
      "link": "https://getnavi.jp/capa/exhibition/tokyo/",
      "tag": "exhibition"
    },
    {
      "title": "ファトマ・ハッスーナ「ユニセフ職員が見たガザの子どもたち」",
      "start_date": "2026-12-11",
      "end_date": "2026-02-19",
      "location": "ユニセフハウス",
      "date_text": "12/11～2/19",
      "link": "https://getnavi.jp/capa/exhibition/tokyo/",
      "tag": "exhibition"
    },
    {
      "title": "佐藤健寿写真展",
      "start_date": "2026-11-14",
      "end_date": "2026-02-12",
      "location": "ライカ大丸東京店【大丸東京店10F】",
      "date_text": "11/14～2/12",
      "link": "https://getnavi.jp/capa/exhibition/tokyo/",
      "tag": "exhibition"
    },
    {
      "title": "大丸有フォトアーカイブ みんなの写真展 – まちの魅力",
      "start_date": "2026-02-04",
      "end_date": "2026-02-14",
      "location": "GOOD DESIGN Marunouchi",
      "date_text": "2/4～14",
      "link": "https://getnavi.jp/capa/exhibition/tokyo/",
      "tag": "exhibition"
    },
    {
      "title": "写真展 ハリウッドの名監督たち 映画芸術科学アカデミーのコレクションより",
      "start_date": "2026-12-16",
      "end_date": "2026-03-22",
      "location": "国立映画アーカイブ 7F展示室",
      "date_text": "12/16～3/22",
      "link": "https://getnavi.jp/capa/exhibition/tokyo/",
      "tag": "exhibition"
    },
    {
      "title": "大西茂 写真と絵画",
      "start_date": "2026-01-31",
      "end_date": "2026-03-29",
      "location": "東京ステーションギャラリー",
      "date_text": "1/31～3/29",
      "link": "https://getnavi.jp/capa/exhibition/tokyo/",
      "tag": "exhibition"
    },
    {
      "title": "丸の内写真教室「東京モノクローム」",
      "start_date": "2026-12-24",
      "end_date": "2026-02-28",
      "location": "丸の内フォトギャラリー",
      "date_text": "12/24～2/28",
      "link": "https://getnavi.jp/capa/exhibition/tokyo/",
      "tag": "exhibition"
    },
    {
      "title": "鬼海弘雄「PERSONA – 坂東玉三郎」",
      "start_date": "2026-01-05",
      "end_date": "2026-03-31",
      "location": "フジフイルム スクエア",
      "date_text": "1/5～3/31",
      "link": "https://getnavi.jp/capa/exhibition/tokyo/",
      "tag": "exhibition"
    },
    {
      "title": "前田ケイジ「冬ざれへの誘い」",
      "start_date": "2026-01-30",
      "end_date": "2026-02-05",
      "location": "フジフイルム スクエア",
      "date_text": "1/30～2/5",
      "link": "https://getnavi.jp/capa/exhibition/tokyo/",
      "tag": "exhibition"
    },
    {
      "title": "竹田義之「海を鎮める」",
      "start_date": "2026-02-06",
      "end_date": "2026-02-12",
      "location": "フジフイルム スクエア",
      "date_text": "2/6～12",
      "link": "https://getnavi.jp/capa/exhibition/tokyo/",
      "tag": "exhibition"
    },
    {
      "title": "中澤勝「雪国」",
      "start_date": "2026-02-13",
      "end_date": "2026-02-19",
      "location": "フジフイルム スクエア",
      "date_text": "2/13～19",
      "link": "https://getnavi.jp/capa/exhibition/tokyo/",
      "tag": "exhibition"
    },
    {
      "title": "岡田敦「ユルリ島の馬」～The Horses of Yururi Island～",
      "start_date": "2026-02-20",
      "end_date": "2026-03-05",
      "location": "フジフイルム スクエア",
      "date_text": "2/20～3/5",
      "link": "https://getnavi.jp/capa/exhibition/tokyo/",
      "tag": "exhibition"
    },
    {
      "title": "第47回 よみうり写真大賞 入賞作品発表展",
      "start_date": "2026-03-06",
      "end_date": "2026-03-12",
      "location": "フジフイルム スクエア",
      "date_text": "3/6～12",
      "link": "https://getnavi.jp/capa/exhibition/tokyo/",
      "tag": "exhibition"
    },
    {
      "title": "ポートフォリオレビュー / アワード2025",
      "start_date": "2026-03-13",
      "end_date": "2026-04-02",
      "location": "フジフイルム スクエア",
      "date_text": "3/13～4/2",
      "link": "https://getnavi.jp/capa/exhibition/tokyo/",
      "tag": "exhibition"
    },
    {
      "title": "石井護「American Journey」",
      "start_date": "2026-01-30",
      "end_date": "2026-02-05",
      "location": "フジフイルム スクエア",
      "date_text": "1/30～2/5",
      "link": "https://getnavi.jp/capa/exhibition/tokyo/",
      "tag": "exhibition"
    },
    {
      "title": "写真集団ポップコーン「東京余白」",
      "start_date": "2026-02-06",
      "end_date": "2026-02-12",
      "location": "フジフイルム スクエア",
      "date_text": "2/6～12",
      "link": "https://getnavi.jp/capa/exhibition/tokyo/",
      "tag": "exhibition"
    },
    {
      "title": "松田康司「命めぐる海の物語」",
      "start_date": "2026-02-13",
      "end_date": "2026-02-26",
      "location": "フジフイルム スクエア",
      "date_text": "2/13～26",
      "link": "https://getnavi.jp/capa/exhibition/tokyo/",
      "tag": "exhibition"
    },
    {
      "title": "鈴島章嘉「想い出の尾瀬風景」",
      "start_date": "2026-02-27",
      "end_date": "2026-03-05",
      "location": "フジフイルム スクエア",
      "date_text": "2/27～3/5",
      "link": "https://getnavi.jp/capa/exhibition/tokyo/",
      "tag": "exhibition"
    },
    {
      "title": "林祐介「Svalbard78°～」～北極圏犬橇350キロの旅～",
      "start_date": "2026-03-06",
      "end_date": "2026-03-12",
      "location": "フジフイルム スクエア",
      "date_text": "3/6～12",
      "link": "https://getnavi.jp/capa/exhibition/tokyo/",
      "tag": "exhibition"
    },
    {
      "title": "ポートフォリオレビュー / アワード2025",
      "start_date": "2026-03-13",
      "end_date": "2026-04-02",
      "location": "フジフイルム スクエア",
      "date_text": "3/13～4/2",
      "link": "https://getnavi.jp/capa/exhibition/tokyo/",
      "tag": "exhibition"
    },
    {
      "title": "富士フイルム海老名Minerva AFC「応援が力に! 歓声が勝利に! ～2025 X1 Super 初勝利！～」",
      "start_date": "2026-01-16",
      "end_date": "2026-02-05",
      "location": "フジフイルム スクエア",
      "date_text": "1/16～2/5",
      "link": "https://getnavi.jp/capa/exhibition/tokyo/",
      "tag": "exhibition"
    },
    {
      "title": "麻布未来写真館 ～次世代へつなぐ麻布の記憶～",
      "start_date": "2026-02-06",
      "end_date": "2026-03-05",
      "location": "フジフイルム スクエア",
      "date_text": "2/6～3/5",
      "link": "https://getnavi.jp/capa/exhibition/tokyo/",
      "tag": "exhibition"
    },
    {
      "title": "富士フイルムグループ「自慢のうちの子ペットフォトコンテスト2025」入賞作品展",
      "start_date": "2026-03-06",
      "end_date": "2026-03-26",
      "location": "フジフイルム スクエア",
      "date_text": "3/6～26",
      "link": "https://getnavi.jp/capa/exhibition/tokyo/",
      "tag": "exhibition"
    },
    {
      "title": "第23回 港区観光フォトコンテスト2025",
      "start_date": "2026-03-27",
      "end_date": "2026-04-02",
      "location": "フジフイルム スクエア",
      "date_text": "3/27～4/2",
      "link": "https://getnavi.jp/capa/exhibition/tokyo/",
      "tag": "exhibition"
    },
    {
      "title": "高橋海斗「Ever-Flowing Life」知床 -めぐりゆく時の中で-",
      "start_date": "2026-01-16",
      "end_date": "2026-02-05",
      "location": "フジフイルム スクエア",
      "date_text": "1/16～2/5",
      "link": "https://getnavi.jp/capa/exhibition/tokyo/",
      "tag": "exhibition"
    },
    {
      "title": "大橋和典「那覇市・農連市場の記憶」-消えゆく市場と暮らしの息遣いの記録-",
      "start_date": "2026-02-06",
      "end_date": "2026-02-19",
      "location": "フジフイルム スクエア",
      "date_text": "2/6～19",
      "link": "https://getnavi.jp/capa/exhibition/tokyo/",
      "tag": "exhibition"
    },
    {
      "title": "Mikael Cronwall「The Swedish Monument / The Godzilla Series」",
      "start_date": "2026-02-20",
      "end_date": "2026-03-05",
      "location": "フジフイルム スクエア",
      "date_text": "2/20～3/5",
      "link": "https://getnavi.jp/capa/exhibition/tokyo/",
      "tag": "exhibition"
    },
    {
      "title": "水谷章人 photographer 60 years「イマージュ・ド・スポール “夢”」",
      "start_date": "2026-03-06",
      "end_date": "2026-03-26",
      "location": "フジフイルム スクエア",
      "date_text": "3/6～26",
      "link": "https://getnavi.jp/capa/exhibition/tokyo/",
      "tag": "exhibition"
    },
    {
      "title": "Japan Photo Meister Club「Neo Japanesque」",
      "start_date": "2026-03-27",
      "end_date": "2026-04-02",
      "location": "フジフイルム スクエア",
      "date_text": "3/27～4/2",
      "link": "https://getnavi.jp/capa/exhibition/tokyo/",
      "tag": "exhibition"
    },
    {
      "title": "三好耕三「1620 CACTI」",
      "start_date": "2026-01-09",
      "end_date": "2026-03-04",
      "location": "PGI",
      "date_text": "1/9～3/4",
      "link": "https://getnavi.jp/capa/exhibition/tokyo/",
      "tag": "exhibition"
    },
    {
      "title": "恵比寿映像祭2026 あなたの音に 日花聲音「Polyphonic Voices Bathed in Sunlight」",
      "start_date": "2026-02-06",
      "end_date": "2026-02-23",
      "location": "東京都写真美術館",
      "date_text": "2/6～23",
      "link": "https://getnavi.jp/capa/exhibition/tokyo/",
      "tag": "exhibition"
    },
    {
      "title": "恵比寿映像祭2026 あなたの音に 日花聲音「Polyphonic Voices Bathed in Sunlight」",
      "start_date": "2026-02-06",
      "end_date": "2026-02-23",
      "location": "東京都写真美術館",
      "date_text": "2/6～23",
      "link": "https://getnavi.jp/capa/exhibition/tokyo/",
      "tag": "exhibition"
    },
    {
      "title": "W.ユージン・スミスとニューヨーク ロフトの時代",
      "start_date": "2026-03-17",
      "end_date": "2026-06-07",
      "location": "東京都写真美術館",
      "date_text": "3/17～6/7",
      "link": "https://getnavi.jp/capa/exhibition/tokyo/",
      "tag": "exhibition"
    },
    {
      "title": "恵比寿映像祭2026 あなたの音に 日花聲音「Polyphonic Voices Bathed in Sunlight」",
      "start_date": "2026-02-06",
      "end_date": "2026-02-23",
      "location": "東京都写真美術館",
      "date_text": "2/6～23",
      "link": "https://getnavi.jp/capa/exhibition/tokyo/",
      "tag": "exhibition"
    },
    {
      "title": "APAアワード 2026",
      "start_date": "2026-02-28",
      "end_date": "2026-03-15",
      "location": "東京都写真美術館",
      "date_text": "2/28～3/15",
      "link": "https://getnavi.jp/capa/exhibition/tokyo/",
      "tag": "exhibition"
    },
    {
      "title": "言葉なき声、密やかな響き – イブオーク チョウテイ 磯谷博史",
      "start_date": "2026-02-05",
      "end_date": "2026-02-15",
      "location": "AL",
      "date_text": "2/5～15",
      "link": "https://getnavi.jp/capa/exhibition/tokyo/",
      "tag": "exhibition"
    },
    {
      "title": "福岡大季「SYNCHRONY」(3/2休館)",
      "start_date": "2026-02-24",
      "end_date": "2026-03-07",
      "location": "CAFE NOOK",
      "date_text": "2/24～3/7",
      "link": "https://getnavi.jp/capa/exhibition/tokyo/",
      "tag": "exhibition"
    },
    {
      "title": "【3・4・5F】JAPAN LEICA USER GROUP写真展2026",
      "start_date": "2026-02-03",
      "end_date": "2026-02-08",
      "location": "ギャラリー・ルデコ",
      "date_text": "2/3～8",
      "link": "https://getnavi.jp/capa/exhibition/tokyo/",
      "tag": "exhibition"
    },
    {
      "title": "【6F】VOICE 浜辺やよい写真展",
      "start_date": "2026-02-03",
      "end_date": "2026-02-08",
      "location": "ギャラリー・ルデコ",
      "date_text": "2/3～8",
      "link": "https://getnavi.jp/capa/exhibition/tokyo/",
      "tag": "exhibition"
    },
    {
      "title": "【4F】私たちは消された展2026",
      "start_date": "2026-02-09",
      "end_date": "2026-02-15",
      "location": "ギャラリー・ルデコ",
      "date_text": "2/9～15",
      "link": "https://getnavi.jp/capa/exhibition/tokyo/",
      "tag": "exhibition"
    },
    {
      "title": "【B1F】『真夜中に挽歌』と私の写真展 ～SOUL NUANCE 3～",
      "start_date": "2026-02-24",
      "end_date": "2026-03-01",
      "location": "ギャラリー・ルデコ",
      "date_text": "2/24～3/1",
      "link": "https://getnavi.jp/capa/exhibition/tokyo/",
      "tag": "exhibition"
    },
    {
      "title": "【3F】美容師のフォトクリエイト展 ARIMINO PHOTO PRESENTATION2025",
      "start_date": "2026-02-10",
      "end_date": "2026-02-15",
      "location": "ギャラリー・ルデコ",
      "date_text": "2/10～15",
      "link": "https://getnavi.jp/capa/exhibition/tokyo/",
      "tag": "exhibition"
    },
    {
      "title": "【5F】キヤノンフォトクラブ東京JOY写真展2026",
      "start_date": "2026-02-10",
      "end_date": "2026-02-15",
      "location": "ギャラリー・ルデコ",
      "date_text": "2/10～15",
      "link": "https://getnavi.jp/capa/exhibition/tokyo/",
      "tag": "exhibition"
    },
    {
      "title": "【5F】誰そ彼女展4 (たそかのてん)",
      "start_date": "2026-02-23",
      "end_date": "2026-03-01",
      "location": "ギャラリー・ルデコ",
      "date_text": "2/23～3/1",
      "link": "https://getnavi.jp/capa/exhibition/tokyo/",
      "tag": "exhibition"
    },
    {
      "title": "【4F】奈月セナ ティム・ギャロ「SILLAGE・シヤージュ」",
      "start_date": "2026-02-16",
      "end_date": "2026-02-22",
      "location": "ギャラリー・ルデコ",
      "date_text": "2/16～22",
      "link": "https://getnavi.jp/capa/exhibition/tokyo/",
      "tag": "exhibition"
    },
    {
      "title": "【6F】New Portrait TOKYO 2026",
      "start_date": "2026-02-23",
      "end_date": "2026-03-01",
      "location": "ギャラリー・ルデコ",
      "date_text": "2/23～3/1",
      "link": "https://getnavi.jp/capa/exhibition/tokyo/",
      "tag": "exhibition"
    },
    {
      "title": "【3F】ALICE NANASE BIRTHDAY PHOTO EXHIBITION",
      "start_date": "2026-02-24",
      "end_date": "2026-03-01",
      "location": "ギャラリー・ルデコ",
      "date_text": "2/24～3/1",
      "link": "https://getnavi.jp/capa/exhibition/tokyo/",
      "tag": "exhibition"
    },
    {
      "title": "AKANE「Supersupercalifragilisticexpialidodocious」",
      "start_date": "2026-02-13",
      "end_date": "2026-02-21",
      "location": "MIDORI荘 中目黒ギャラリー",
      "date_text": "2/13～21",
      "link": "https://getnavi.jp/capa/exhibition/tokyo/",
      "tag": "exhibition"
    },
    {
      "title": "ワーナー・ビショフの昭和 ～日本が日本でなかったあの頃～",
      "start_date": "2026-12-05",
      "end_date": "2026-03-03",
      "location": "ライカギャラリー表参道【ライカ表参道店2F】",
      "date_text": "12/5～3/3",
      "link": "https://getnavi.jp/capa/exhibition/tokyo/",
      "tag": "exhibition"
    },
    {
      "title": "「Monochrome」展 前期",
      "start_date": "2026-01-15",
      "end_date": "2026-02-16",
      "location": "GR SPACE TOKYO",
      "date_text": "1/15～2/16",
      "link": "https://getnavi.jp/capa/exhibition/tokyo/",
      "tag": "exhibition"
    },
    {
      "title": "「Monochrome」展 後期",
      "start_date": "2026-02-19",
      "end_date": "2026-03-23",
      "location": "GR SPACE TOKYO",
      "date_text": "2/19～3/23",
      "link": "https://getnavi.jp/capa/exhibition/tokyo/",
      "tag": "exhibition"
    },
    {
      "title": "飯豊まりえ「日々の裏地。或いは、覚え書き。」",
      "start_date": "2026-01-30",
      "end_date": "2026-02-12",
      "location": "LUMIX BASE TOKYO",
      "date_text": "1/30～2/12",
      "link": "https://getnavi.jp/capa/exhibition/tokyo/",
      "tag": "exhibition"
    },
    {
      "title": "吉岡來美「少女図鑑」",
      "start_date": "2026-02-03",
      "end_date": "2026-02-08",
      "location": "Nine Gallery",
      "date_text": "2/3～8",
      "link": "https://getnavi.jp/capa/exhibition/tokyo/",
      "tag": "exhibition"
    },
    {
      "title": "山本寛人「幽玄ノ美」",
      "start_date": "2026-02-10",
      "end_date": "2026-02-25",
      "location": "Nine Gallery",
      "date_text": "2/10～25",
      "link": "https://getnavi.jp/capa/exhibition/tokyo/",
      "tag": "exhibition"
    },
    {
      "title": "昭和100年記念 昭和のカメラ物語 第二部 : 1955-1989",
      "start_date": "2026-02-10",
      "end_date": "2026-06-21",
      "location": "JCII",
      "date_text": "2/10～6/21",
      "link": "https://getnavi.jp/capa/exhibition/tokyo/",
      "tag": "exhibition"
    },
    {
      "title": "幕末・明治の古写真展「盛岡の収集家・村田明コレクション Part I」",
      "start_date": "2026-02-03",
      "end_date": "2026-03-01",
      "location": "JCII",
      "date_text": "2/3～3/1",
      "link": "https://getnavi.jp/capa/exhibition/tokyo/",
      "tag": "exhibition"
    },
    {
      "title": "杉山吉良「-松永安左ヱ門生誕150年- 美しき巨人」",
      "start_date": "2026-03-03",
      "end_date": "2026-03-29",
      "location": "JCII",
      "date_text": "3/3～29",
      "link": "https://getnavi.jp/capa/exhibition/tokyo/",
      "tag": "exhibition"
    },
    {
      "title": "OM SYSTEMズイコークラブ東京支部「私の好きなフォト」",
      "start_date": "2026-02-03",
      "end_date": "2026-02-08",
      "location": "JCII",
      "date_text": "2/3～8",
      "link": "https://getnavi.jp/capa/exhibition/tokyo/",
      "tag": "exhibition"
    },
    {
      "title": "キヤノンOBフォトメイト 第14回 写真展",
      "start_date": "2026-02-10",
      "end_date": "2026-02-15",
      "location": "JCII",
      "date_text": "2/10～15",
      "link": "https://getnavi.jp/capa/exhibition/tokyo/",
      "tag": "exhibition"
    },
    {
      "title": "第22回 HAKUHODO 錦会カメラ倶楽部作品展",
      "start_date": "2026-02-17",
      "end_date": "2026-02-23",
      "location": "JCII",
      "date_text": "2/17～23",
      "link": "https://getnavi.jp/capa/exhibition/tokyo/",
      "tag": "exhibition"
    },
    {
      "title": "第6回 五人展",
      "start_date": "2026-02-25",
      "end_date": "2026-03-01",
      "location": "JCII",
      "date_text": "2/25～3/1",
      "link": "https://getnavi.jp/capa/exhibition/tokyo/",
      "tag": "exhibition"
    },
    {
      "title": "第21回 建て物写真展",
      "start_date": "2026-03-03",
      "end_date": "2026-03-08",
      "location": "JCII",
      "date_text": "3/3～8",
      "link": "https://getnavi.jp/capa/exhibition/tokyo/",
      "tag": "exhibition"
    },
    {
      "title": "勝木繁夫「屋久島 龍をさがす」",
      "start_date": "2026-03-10",
      "end_date": "2026-03-15",
      "location": "JCII",
      "date_text": "3/10～15",
      "link": "https://getnavi.jp/capa/exhibition/tokyo/",
      "tag": "exhibition"
    },
    {
      "title": "第12回 神吉教室写真展",
      "start_date": "2026-03-17",
      "end_date": "2026-03-22",
      "location": "JCII",
      "date_text": "3/17～22",
      "link": "https://getnavi.jp/capa/exhibition/tokyo/",
      "tag": "exhibition"
    },
    {
      "title": "目黒さんまの会「宇宙分の一 2026」",
      "start_date": "2026-03-24",
      "end_date": "2026-03-29",
      "location": "JCII",
      "date_text": "3/24～29",
      "link": "https://getnavi.jp/capa/exhibition/tokyo/",
      "tag": "exhibition"
    },
    {
      "title": "篠田烈「デジャヴュ (déjà vu) 記憶の街」",
      "start_date": "2026-12-10",
      "end_date": "2026-02-14",
      "location": "gallery bauhaus",
      "date_text": "12/10～2/14",
      "link": "https://getnavi.jp/capa/exhibition/tokyo/",
      "tag": "exhibition"
    },
    {
      "title": "小瀧達郎「サウダージ -リスボンからサンタクルスへ-」(5/3～6休館)",
      "start_date": "2026-02-25",
      "end_date": "2026-05-23",
      "location": "gallery bauhaus",
      "date_text": "2/25～5/23",
      "link": "https://getnavi.jp/capa/exhibition/tokyo/",
      "tag": "exhibition"
    },
    {
      "title": "齊藤小弥太「土地の記憶 V」",
      "start_date": "2026-01-27",
      "end_date": "2026-02-08",
      "location": "TOKYO BRIGHT GALLERY",
      "date_text": "1/27～2/8",
      "link": "https://getnavi.jp/capa/exhibition/tokyo/",
      "tag": "exhibition"
    },
    {
      "title": "小園井和生「5泊6日」",
      "start_date": "2026-02-10",
      "end_date": "2026-02-22",
      "location": "TOKYO BRIGHT GALLERY",
      "date_text": "2/10～22",
      "link": "https://getnavi.jp/capa/exhibition/tokyo/",
      "tag": "exhibition"
    },
    {
      "title": "佑木瞬「ふれる花が舞い落ちる方に」",
      "start_date": "2026-02-03",
      "end_date": "2026-02-08",
      "location": "Roonee 247 Fine arts",
      "date_text": "2/3～8",
      "link": "https://getnavi.jp/capa/exhibition/tokyo/",
      "tag": "exhibition"
    },
    {
      "title": "針穴研究会「第十回 はりけん研究発表展」",
      "start_date": "2026-02-11",
      "end_date": "2026-02-15",
      "location": "Roonee 247 Fine arts",
      "date_text": "2/11～15",
      "link": "https://getnavi.jp/capa/exhibition/tokyo/",
      "tag": "exhibition"
    },
    {
      "title": "田中昭二「INTO THE BLUE」",
      "start_date": "2026-02-19",
      "end_date": "2026-03-01",
      "location": "Roonee 247 Fine arts",
      "date_text": "2/19～3/1",
      "link": "https://getnavi.jp/capa/exhibition/tokyo/",
      "tag": "exhibition"
    },
    {
      "title": "本山周平エキシビジョンゼミ「あわいと曙光の中に ～Emerging within the light of dawn～」",
      "start_date": "2026-03-03",
      "end_date": "2026-03-15",
      "location": "Roonee 247 Fine arts",
      "date_text": "3/3～15",
      "link": "https://getnavi.jp/capa/exhibition/tokyo/",
      "tag": "exhibition"
    },
    {
      "title": "田中昭二「INTO THE BLUE」",
      "start_date": "2026-02-19",
      "end_date": "2026-03-01",
      "location": "Roonee 247 Fine arts",
      "date_text": "2/19～3/1",
      "link": "https://getnavi.jp/capa/exhibition/tokyo/",
      "tag": "exhibition"
    },
    {
      "title": "本山周平エキシビジョンゼミ「あわいと曙光の中に ～Emerging within the light of dawn～」",
      "start_date": "2026-03-03",
      "end_date": "2026-03-15",
      "location": "Roonee 247 Fine arts",
      "date_text": "3/3～15",
      "link": "https://getnavi.jp/capa/exhibition/tokyo/",
      "tag": "exhibition"
    },
    {
      "title": "土佐和史「THE SUNLIGHT TOURS」",
      "start_date": "2026-02-03",
      "end_date": "2026-03-01",
      "location": "Roonee 247 Fine arts",
      "date_text": "2/3～3/1",
      "link": "https://getnavi.jp/capa/exhibition/tokyo/",
      "tag": "exhibition"
    },
    {
      "title": "是政んぽ KoreMasampO",
      "start_date": "2026-02-07",
      "end_date": "2026-02-15",
      "location": "ぎゃらりーKnulp",
      "date_text": "2/7～15",
      "link": "https://getnavi.jp/capa/exhibition/tokyo/",
      "tag": "exhibition"
    },
    {
      "title": "第171回公募展 さむ〜い冬の物語 vol.3",
      "start_date": "2026-02-21",
      "end_date": "2026-03-01",
      "location": "ぎゃらりーKnulp",
      "date_text": "2/21～3/1",
      "link": "https://getnavi.jp/capa/exhibition/tokyo/",
      "tag": "exhibition"
    },
    {
      "title": "第172回公募展 旅の欠片 – 風景が運ぶ記憶",
      "start_date": "2026-03-07",
      "end_date": "2026-03-15",
      "location": "ぎゃらりーKnulp",
      "date_text": "3/7～15",
      "link": "https://getnavi.jp/capa/exhibition/tokyo/",
      "tag": "exhibition"
    },
    {
      "title": "古里裕美「TIDE」",
      "start_date": "2026-01-09",
      "end_date": "2026-03-20",
      "location": "KOSHA KOSHA AKIHABARA",
      "date_text": "1/9～3/20",
      "link": "https://getnavi.jp/capa/exhibition/tokyo/",
      "tag": "exhibition"
    },
    {
      "title": "【SideA/SideB】すぎもとももか「ねこのせなか」",
      "start_date": "2026-01-09",
      "end_date": "2026-02-21",
      "location": "KOSHA KOSHA AKIHABARA",
      "date_text": "1/9～2/21",
      "link": "https://getnavi.jp/capa/exhibition/tokyo/",
      "tag": "exhibition"
    },
    {
      "title": "ねこ休み展 冬 2026",
      "start_date": "2026-01-23",
      "end_date": "2026-02-23",
      "location": "TODAYS GALLERY STUDIO.",
      "date_text": "1/23～2/23",
      "link": "https://getnavi.jp/capa/exhibition/tokyo/",
      "tag": "exhibition"
    },
    {
      "title": "変わる廃墟展 2026",
      "start_date": "2026-02-27",
      "end_date": "2026-03-29",
      "location": "TODAYS GALLERY STUDIO.",
      "date_text": "2/27～3/29",
      "link": "https://getnavi.jp/capa/exhibition/tokyo/",
      "tag": "exhibition"
    },
    {
      "title": "秋元貴美子「遥かの祀り」",
      "start_date": "2026-02-10",
      "end_date": "2026-02-15",
      "location": "ピクトリコ ショップ＆ギャラリー",
      "date_text": "2/10～15",
      "link": "https://getnavi.jp/capa/exhibition/tokyo/",
      "tag": "exhibition"
    },
    {
      "title": "第2回ウズベキスタン・フォトコンテスト写真展",
      "start_date": "2026-02-20",
      "end_date": "2026-02-22",
      "location": "ピクトリコ ショップ＆ギャラリー",
      "date_text": "2/20～22",
      "link": "https://getnavi.jp/capa/exhibition/tokyo/",
      "tag": "exhibition"
    },
    {
      "title": "クロダユキ「シマノケ」",
      "start_date": "2026-02-24",
      "end_date": "2026-03-08",
      "location": "ピクトリコ ショップ＆ギャラリー",
      "date_text": "2/24～3/8",
      "link": "https://getnavi.jp/capa/exhibition/tokyo/",
      "tag": "exhibition"
    },
    {
      "title": "片平孝「塩の旅 ～地球の塩の現場に立つ～」",
      "start_date": "2026-01-31",
      "end_date": "2026-04-05",
      "location": "たばこと塩の博物館",
      "date_text": "1/31～4/5",
      "link": "https://getnavi.jp/capa/exhibition/tokyo/",
      "tag": "exhibition"
    },
    {
      "title": "波多野祐貴「In Other Rooms」",
      "start_date": "2026-01-23",
      "end_date": "2026-02-04",
      "location": "Alt_Medium",
      "date_text": "1/23～2/4",
      "link": "https://getnavi.jp/capa/exhibition/tokyo/",
      "tag": "exhibition"
    },
    {
      "title": "高橋恭介「カリモーチョな空 – In liminality」",
      "start_date": "2026-02-20",
      "end_date": "2026-02-25",
      "location": "Alt_Medium",
      "date_text": "2/20～25",
      "link": "https://getnavi.jp/capa/exhibition/tokyo/",
      "tag": "exhibition"
    },
    {
      "title": "Rinaty「#自分を好きになるためのセルフポートレート」",
      "start_date": "2026-01-21",
      "end_date": "2026-02-02",
      "location": "ケンコー・トキナーギャラリー",
      "date_text": "1/21～2/2",
      "link": "https://getnavi.jp/capa/exhibition/tokyo/",
      "tag": "exhibition"
    },
    {
      "title": "ケンコー・トキナー あずのの撮影会展",
      "start_date": "2026-02-04",
      "end_date": "2026-02-16",
      "location": "ケンコー・トキナーギャラリー",
      "date_text": "2/4～16",
      "link": "https://getnavi.jp/capa/exhibition/tokyo/",
      "tag": "exhibition"
    },
    {
      "title": "タムタク画像処理講座 生徒合同写真展",
      "start_date": "2026-02-18",
      "end_date": "2026-03-02",
      "location": "ケンコー・トキナーギャラリー",
      "date_text": "2/18～3/2",
      "link": "https://getnavi.jp/capa/exhibition/tokyo/",
      "tag": "exhibition"
    },
    {
      "title": "坂井田富三「成田詣」",
      "start_date": "2026-03-04",
      "end_date": "2026-03-16",
      "location": "ケンコー・トキナーギャラリー",
      "date_text": "3/4～16",
      "link": "https://getnavi.jp/capa/exhibition/tokyo/",
      "tag": "exhibition"
    },
    {
      "title": "篠利幸「Toshi, ’o sole mio！ – トシ、あなたは私の太陽 -」",
      "start_date": "2026-02-06",
      "end_date": "2026-02-28",
      "location": "ギャラリー冬青",
      "date_text": "2/6～28",
      "link": "https://getnavi.jp/capa/exhibition/tokyo/",
      "tag": "exhibition"
    },
    {
      "title": "2026フォックス・タルボット賞受賞写真展",
      "start_date": "2026-02-24",
      "end_date": "2026-03-21",
      "location": "写大ギャラリー【東京工芸大学 中野キャンパス 芸術情報館2F】",
      "date_text": "2/24～3/21",
      "link": "https://getnavi.jp/capa/exhibition/tokyo/",
      "tag": "exhibition"
    },
    {
      "title": "新山清「樹々」(要予約)",
      "start_date": "2026-01-27",
      "end_date": "2026-02-08",
      "location": "Jam Photo Gallery",
      "date_text": "1/27～2/8",
      "link": "https://getnavi.jp/capa/exhibition/tokyo/",
      "tag": "exhibition"
    },
    {
      "title": "クマクラトオル「みんな星のかけらでできてゐる」",
      "start_date": "2026-03-03",
      "end_date": "2026-03-08",
      "location": "Jam Photo Gallery",
      "date_text": "3/3～8",
      "link": "https://getnavi.jp/capa/exhibition/tokyo/",
      "tag": "exhibition"
    },
    {
      "title": "雑誌『写真』vol.8刊行記念 坂本陽「Telescope」",
      "start_date": "2026-01-30",
      "end_date": "2026-03-01",
      "location": "ふげん社",
      "date_text": "1/30～3/1",
      "link": "https://getnavi.jp/capa/exhibition/tokyo/",
      "tag": "exhibition"
    },
    {
      "title": "濱田英明「Haru and Mina」",
      "start_date": "2026-02-05",
      "end_date": "2026-02-24",
      "location": "BOOK AND SONS",
      "date_text": "2/5～24",
      "link": "https://getnavi.jp/capa/exhibition/tokyo/",
      "tag": "exhibition"
    },
    {
      "title": "鋤田正義「SUKITA : Photographs from Early Fashion to Rock Icons」",
      "start_date": "2026-10-29",
      "end_date": "2026-02-15",
      "location": "Blitz Gallery",
      "date_text": "10/29～2/15",
      "link": "https://getnavi.jp/capa/exhibition/tokyo/",
      "tag": "exhibition"
    },
    {
      "title": "日本写真芸術専門学校 総合写真研究ゼミ進級展「Gen Zone」",
      "start_date": "2026-02-04",
      "end_date": "2026-02-08",
      "location": "目黒区美術館 区民ギャラリー",
      "date_text": "2/4～8",
      "link": "https://getnavi.jp/capa/exhibition/tokyo/",
      "tag": "exhibition"
    },
    {
      "title": "ロベール・ドアノー「Robert Doisneau」",
      "start_date": "2026-01-30",
      "end_date": "2026-04-12",
      "location": "art cruise gallery by Baycrew’s",
      "date_text": "1/30～4/12",
      "link": "https://getnavi.jp/capa/exhibition/tokyo/",
      "tag": "exhibition"
    },
    {
      "title": "Songs vol.9",
      "start_date": "2026-02-04",
      "end_date": "2026-02-15",
      "location": "NADAR (ナダール)",
      "date_text": "2/4～15",
      "link": "https://getnavi.jp/capa/exhibition/tokyo/",
      "tag": "exhibition"
    },
    {
      "title": "オールドレンズ写真展",
      "start_date": "2026-02-18",
      "end_date": "2026-03-01",
      "location": "NADAR (ナダール)",
      "date_text": "2/18～3/1",
      "link": "https://getnavi.jp/capa/exhibition/tokyo/",
      "tag": "exhibition"
    },
    {
      "title": "野村佐紀子「Lirio」",
      "start_date": "2026-01-29",
      "end_date": "2026-03-02",
      "location": "book obscura",
      "date_text": "1/29～3/2",
      "link": "https://getnavi.jp/capa/exhibition/tokyo/",
      "tag": "exhibition"
    },
    {
      "title": "2025年 私のこの一枚写真展",
      "start_date": "2026-01-28",
      "end_date": "2026-02-08",
      "location": "町田市フォトサロン",
      "date_text": "1/28～2/8",
      "link": "https://getnavi.jp/capa/exhibition/tokyo/",
      "tag": "exhibition"
    },
    {
      "title": "うめ写真展",
      "start_date": "2026-02-12",
      "end_date": "2026-03-02",
      "location": "町田市フォトサロン",
      "date_text": "2/12～3/2",
      "link": "https://getnavi.jp/capa/exhibition/tokyo/",
      "tag": "exhibition"
    },
    {
      "title": "桜美林大学映像写真サークル「ゆめ 一人ひとり、違うもの」",
      "start_date": "2026-03-04",
      "end_date": "2026-03-09",
      "location": "町田市フォトサロン",
      "date_text": "3/4～9",
      "link": "https://getnavi.jp/capa/exhibition/tokyo/",
      "tag": "exhibition"
    },
    {
      "title": "JA南写真同好会写真展",
      "start_date": "2026-03-11",
      "end_date": "2026-03-16",
      "location": "町田市フォトサロン",
      "date_text": "3/11～16",
      "link": "https://getnavi.jp/capa/exhibition/tokyo/",
      "tag": "exhibition"
    },
    {
      "title": "町田市写真協会 第13回会員選抜写真展",
      "start_date": "2026-02-18",
      "end_date": "2026-02-23",
      "location": "町田市フォトサロン",
      "date_text": "2/18～23",
      "link": "https://getnavi.jp/capa/exhibition/tokyo/",
      "tag": "exhibition"
    },
    {
      "title": "第76回ツバキ展",
      "start_date": "2026-03-06",
      "end_date": "2026-03-08",
      "location": "町田市フォトサロン",
      "date_text": "3/6～8",
      "link": "https://getnavi.jp/capa/exhibition/tokyo/",
      "tag": "exhibition"
    },
    {
      "title": "フォトクラブとってみる会作品展",
      "start_date": "2026-03-25",
      "end_date": "2026-03-30",
      "location": "町田市フォトサロン",
      "date_text": "3/25～30",
      "link": "https://getnavi.jp/capa/exhibition/tokyo/",
      "tag": "exhibition"
    },
    {
      "title": "コニカミノルタ写真班 第37回作品展",
      "start_date": "2026-02-19",
      "end_date": "2026-02-23",
      "location": "まち・なかギャラリーホール 2F",
      "date_text": "2/19～23",
      "link": "https://getnavi.jp/capa/exhibition/tokyo/",
      "tag": "exhibition"
    }
  ]
}